[{"name": "benchmarks.PreprocessingBenchmarks.time_apply_strategy_beginning", "idx": 0, "pretty_name": "benchmarks.PreprocessingBenchmarks.time_apply_strategy_beginning(32, 'balanced', False)", "last_rev": 38, "last_value": 9.453846460180094e-05, "last_err": 0.0, "prev_value": null, "change_rev": null}, {"name": "benchmarks.PreprocessingBenchmarks.time_apply_strategy_beginning", "idx": 1, "pretty_name": "benchmarks.PreprocessingBenchmarks.time_apply_strategy_beginning(32, 'balanced', True)", "last_rev": 38, "last_value": 9.420014035087656e-05, "last_err": 0.0, "prev_value": null, "change_rev": null}, {"name": "benchmarks.PreprocessingBenchmarks.time_apply_strategy_beginning", "idx": 2, "pretty_name": "benchmarks.PreprocessingBenchmarks.time_apply_strategy_beginning(32, 'g_only', False)", "last_rev": 38, "last_value": 9.190011304347008e-05, "last_err": 0.0, "prev_value": null, "change_rev": null}, {"name": "benchmarks.PreprocessingBenchmarks.time_apply_strategy_beginning", "idx": 3, "pretty_name": "benchmarks.PreprocessingBenchmarks.time_apply_strategy_beginning(32, 'g_only', True)", "last_rev": 38, "last_value": 9.306249565220217e-05, "last_err": 0.0, "prev_value": null, "change_rev": null}, {"name": "benchmarks.PreprocessingBenchmarks.time_apply_strategy_beginning", "idx": 4, "pretty_name": "benchmarks.PreprocessingBenchmarks.time_apply_strategy_beginning(32, 'ri_only', False)", "last_rev": 38, "last_value": 9.611132589285428e-05, "last_err": 0.0, "prev_value": null, "change_rev": null}, {"name": "benchmarks.PreprocessingBenchmarks.time_apply_strategy_beginning", "idx": 5, "pretty_name": "benchmarks.PreprocessingBenchmarks.time_apply_strategy_beginning(32, 'ri_only', True)", "last_rev": 38, "last_value": 9.418586403507452e-05, "last_err": 0.0, "prev_value": null, "change_rev": null}, {"name": "benchmarks.PreprocessingBenchmarks.time_apply_strategy_beginning", "idx": 6, "pretty_name": "benchmarks.PreprocessingBenchmarks.time_apply_strategy_beginning(700, 'balanced', False)", "last_rev": 38, "last_value": 0.00012007391666664091, "last_err": 0.0, "prev_value": null, "change_rev": null}, {"name": "benchmarks.PreprocessingBenchmarks.time_apply_strategy_beginning", "idx": 7, "pretty_name": "benchmarks.PreprocessingBenchmarks.time_apply_strategy_beginning(700, 'balanced', True)", "last_rev": 38, "last_value": 0.00011978169999997432, "last_err": 0.0, "prev_value": null, "change_rev": null}, {"name": "benchmarks.PreprocessingBenchmarks.time_apply_strategy_beginning", "idx": 8, "pretty_name": "benchmarks.PreprocessingBenchmarks.time_apply_strategy_beginning(700, 'g_only', False)", "last_rev": 38, "last_value": 0.0001076371313131679, "last_err": 0.0, "prev_value": null, "change_rev": null}, {"name": "benchmarks.PreprocessingBenchmarks.time_apply_strategy_beginning", "idx": 9, "pretty_name": "benchmarks.PreprocessingBenchmarks.time_apply_strategy_beginning(700, 'g_only', True)", "last_rev": 38, "last_value": 0.00010784836499997397, "last_err": 0.0, "prev_value": null, "change_rev": null}, {"name": "benchmarks.PreprocessingBenchmarks.time_apply_strategy_beginning", "idx": 10, "pretty_name": "benchmarks.PreprocessingBenchmarks.time_apply_strategy_beginning(700, 'ri_only', False)", "last_rev": 38, "last_value": 0.00011421708064513462, "last_err": 0.0, "prev_value": null, "change_rev": null}, {"name": "benchmarks.PreprocessingBenchmarks.time_apply_strategy_beginning", "idx": 11, "pretty_name": "benchmarks.PreprocessingBenchmarks.time_apply_strategy_beginning(700, 'ri_only', True)", "last_rev": 38, "last_value": 0.00011425034946237932, "last_err": 0.0, "prev_value": null, "change_rev": null}, {"name": "benchmarks.PreprocessingBenchmarks.time_apply_strategy_beginning", "idx": 12, "pretty_name": "benchmarks.PreprocessingBenchmarks.time_apply_strategy_beginning(4096, 'balanced', False)", "last_rev": 38, "last_value": 0.00029486504285724125, "last_err": 0.0, "prev_value": null, "change_rev": null}, {"name": "benchmarks.PreprocessingBenchmarks.time_apply_strategy_beginning", "idx": 13, "pretty_name": "benchmarks.PreprocessingBenchmarks.time_apply_strategy_beginning(4096, 'balanced', True)", "last_rev": 38, "last_value": 0.00029503632432437144, "last_err": 0.0, "prev_value": null, "change_rev": null}, {"name": "benchmarks.PreprocessingBenchmarks.time_apply_strategy_beginning", "idx": 14, "pretty_name": "benchmarks.PreprocessingBenchmarks.time_apply_strategy_beginning(4096, 'g_only', False)", "last_rev": 38, "last_value": 0.0001868009000000241, "last_err": 0.0, "prev_value": null, "change_rev": null}, {"name": "benchmarks.PreprocessingBenchmarks.time_apply_strategy_beginning", "idx": 15, "pretty_name": "benchmarks.PreprocessingBenchmarks.time_apply_strategy_beginning(4096, 'g_only', True)", "last_rev": 38, "last_value": 0.00018653619090911052, "last_err": 0.0, "prev_value": null, "change_rev": null}, {"name": "benchmarks.PreprocessingBenchmarks.time_apply_strategy_beginning", "idx": 16, "pretty_name": "benchmarks.PreprocessingBenchmarks.time_apply_strategy_beginning(4096, 'ri_only', False)", "last_rev": 38, "last_value": 0.00026206403658534673, "last_err": 0.0, "prev_value": null, "change_rev": null}, {"name": "benchmarks.PreprocessingBenchmarks.time_apply_strategy_beginning", "idx": 17, "pretty_name": "benchmarks.PreprocessingBenchmarks.time_apply_strategy_beginning(4096, 'ri_only', True)", "last_rev": 38, "last_value": 0.00026586075000007976, "last_err": 0.0, "prev_value": null, "change_rev": null}, {"name": "benchmarks.PreprocessingBenchmarks.time_argsort", "idx": 0, "pretty_name": "benchmarks.PreprocessingBenchmarks.time_argsort(32, 'balanced', False)", "last_rev": 38, "last_value": 3.5660702465943066e-06, "last_err": 0.0, "prev_value": 3.631830172984787e-06, "change_rev": [22, 38]}, {"name": "benchmarks.PreprocessingBenchmarks.time_argsort", "idx": 1, "pretty_name": "benchmarks.PreprocessingBenchmarks.time_argsort(32, 'balanced', True)", "last_rev": 38, "last_value": 1.0567124691216046e-07, "last_err": 0.0, "prev_value": 1.0417922100687495e-07, "change_rev": [22, 38]}, {"name": "benchmarks.PreprocessingBenchmarks.time_argsort", "idx": 2, "pretty_name": "benchmarks.PreprocessingBenchmarks.time_argsort(32, 'g_only', False)", "last_rev": 38, "last_value": 3.5845224422476996e-06, "last_err": 2.3344728269450125e-08, "prev_value": null, "change_rev": null}, {"name": "benchmarks.PreprocessingBenchmarks.time_argsort", "idx": 3, "pretty_name": "benchmarks.PreprocessingBenchmarks.time_argsort(32, 'g_only', True)", "last_rev": 38, "last_value": 1.0433368921765608e-07, "last_err": 0.0, "prev_value": 1.0291295707476518e-07, "change_rev": [22, 38]}, {"name": "benchmarks.PreprocessingBenchmarks.time_argsort", "idx": 4, "pretty_name": "benchmarks.PreprocessingBenchmarks.time_argsort(32, 'ri_only', False)", "last_rev": 38, "last_value": 3.6234965618861348e-06, "last_err": 3.404009694826062e-08, "prev_value": null, "change_rev": null}, {"name": "benchmarks.PreprocessingBenchmarks.time_argsort", "idx": 5, "pretty_name": "benchmarks.PreprocessingBenchmarks.time_argsort(32, 'ri_only', True)", "last_rev": 38, "last_value": 1.0603877348609126e-07, "last_err": 0.0, "prev_value": 1.0604736363646338e-07, "change_rev": [22, 38]}, {"name": "benchmarks.PreprocessingBenchmarks.time_argsort", "idx": 6, "pretty_name": "benchmarks.PreprocessingBenchmarks.time_argsort(700, 'balanced', False)", "last_rev": 38, "last_value": 1.816276061121316e-05, "last_err": 0.0, "prev_value": 1.83321395939093e-05, "change_rev": [22, 38]}, {"name": "benchmarks.PreprocessingBenchmarks.time_argsort", "idx": 7, "pretty_name": "benchmarks.PreprocessingBenchmarks.time_argsort(700, 'balanced', True)", "last_rev": 38, "last_value": 1.0416389545456054e-07, "last_err": 0.0, "prev_value": 1.0386205000000617e-07, "change_rev": [22, 38]}, {"name": "benchmarks.PreprocessingBenchmarks.time_argsort", "idx": 8, "pretty_name": "benchmarks.PreprocessingBenchmarks.time_argsort(700, 'g_only', False)", "last_rev": 38, "last_value": 1.7989196517408937e-05, "last_err": 0.0, "prev_value": 1.824187542374612e-05, "change_rev": [22, 38]}, {"name": "benchmarks.PreprocessingBenchmarks.time_argsort", "idx": 9, "pretty_name": "benchmarks.PreprocessingBenchmarks.time_argsort(700, 'g_only', True)", "last_rev": 38, "last_value": 1.0106296818176733e-07, "last_err": 9.969439393992802e-10, "prev_value": null, "change_rev": null}, {"name": "benchmarks.PreprocessingBenchmarks.time_argsort", "idx": 10, "pretty_name": "benchmarks.PreprocessingBenchmarks.time_argsort(700, 'ri_only', False)", "last_rev": 38, "last_value": 1.8115508361199184e-05, "last_err": 0.0, "prev_value": 1.8247631756765286e-05, "change_rev": [22, 38]}, {"name": "benchmarks.PreprocessingBenchmarks.time_argsort", "idx": 11, "pretty_name": "benchmarks.PreprocessingBenchmarks.time_argsort(700, 'ri_only', True)", "last_rev": 38, "last_value": 1.0162164999989252e-07, "last_err": 9.580612929683437e-10, "prev_value": null, "change_rev": null}, {"name": "benchmarks.PreprocessingBenchmarks.time_argsort", "idx": 12, "pretty_name": "benchmarks.PreprocessingBenchmarks.time_argsort(4096, 'balanced', False)", "last_rev": 38, "last_value": 8.882644672134293e-05, "last_err": 0.0, "prev_value": 8.9135462809908e-05, "change_rev": [22, 38]}, {"name": "benchmarks.PreprocessingBenchmarks.time_argsort", "idx": 13, "pretty_name": "benchmarks.PreprocessingBenchmarks.time_argsort(4096, 'balanced', True)", "last_rev": 38, "last_value": 1.0291855454547452e-07, "last_err": 0.0, "prev_value": 1.0239351818186874e-07, "change_rev": [22, 38]}, {"name": "benchmarks.PreprocessingBenchmarks.time_argsort", "idx": 14, "pretty_name": "benchmarks.PreprocessingBenchmarks.time_argsort(4096, 'g_only', False)", "last_rev": 38, "last_value": 8.85075650406598e-05, "last_err": 0.0, "prev_value": 8.898714344258415e-05, "change_rev": [22, 38]}, {"name": "benchmarks.PreprocessingBenchmarks.time_argsort", "idx": 15, "pretty_name": "benchmarks.PreprocessingBenchmarks.time_argsort(4096, 'g_only', True)", "last_rev": 38, "last_value": 1.0142735000002935e-07, "last_err": 0.0, "prev_value": 1.0122305454532663e-07, "change_rev": [22, 38]}, {"name": "benchmarks.PreprocessingBenchmarks.time_argsort", "idx": 16, "pretty_name": "benchmarks.PreprocessingBenchmarks.time_argsort(4096, 'ri_only', False)", "last_rev": 38, "last_value": 8.904768852462496e-05, "last_err": 4.749764423044276e-07, "prev_value": null, "change_rev": null}, {"name": "benchmarks.PreprocessingBenchmarks.time_argsort", "idx": 17, "pretty_name": "benchmarks.PreprocessingBenchmarks.time_argsort(4096, 'ri_only', True)", "last_rev": 38, "last_value": 1.037347954545192e-07, "last_err": 0.0, "prev_value": 1.0465629545460718e-07, "change_rev": [22, 38]}, {"name": "benchmarks.PreprocessingBenchmarks.time_normalize_mag", "idx": 0, "pretty_name": "benchmarks.PreprocessingBenchmarks.time_normalize_mag(32, 'balanced', False)", "last_rev": 38, "last_value": 1.3428854192745881e-05, "last_err": 0.0, "prev_value": 1.350468685567409e-05, "change_rev": [22, 38]}, {"name": "benchmarks.PreprocessingBenchmarks.time_normalize_mag", "idx": 1, "pretty_name": "benchmarks.PreprocessingBenchmarks.time_normalize_mag(32, 'balanced', True)", "last_rev": 38, "last_value": 1.370010243277329e-05, "last_err": 0.0, "prev_value": 1.3997007015309254e-05, "change_rev": [22, 38]}, {"name": "benchmarks.PreprocessingBenchmarks.time_normalize_mag", "idx": 2, "pretty_name": "benchmarks.PreprocessingBenchmarks.time_normalize_mag(32, 'g_only', False)", "last_rev": 38, "last_value": 1.33960456790121e-05, "last_err": 0.0, "prev_value": 1.3461691326534893e-05, "change_rev": [22, 38]}, {"name": "benchmarks.PreprocessingBenchmarks.time_normalize_mag", "idx": 3, "pretty_name": "benchmarks.PreprocessingBenchmarks.time_normalize_mag(32, 'g_only', True)", "last_rev": 38, "last_value": 1.3401238881836374e-05, "last_err": 0.0, "prev_value": 1.3563283718103304e-05, "change_rev": [22, 38]}, {"name": "benchmarks.PreprocessingBenchmarks.time_normalize_mag", "idx": 4, "pretty_name": "benchmarks.PreprocessingBenchmarks.time_normalize_mag(32, 'ri_only', False)", "last_rev": 38, "last_value": 1.3566444711535871e-05, "last_err": 0.0, "prev_value": 1.3398302190711263e-05, "change_rev": [22, 38]}, {"name": "benchmarks.PreprocessingBenchmarks.time_normalize_mag", "idx": 5, "pretty_name": "benchmarks.PreprocessingBenchmarks.time_normalize_mag(32, 'ri_only', True)", "last_rev": 38, "last_value": 1.3468129870126227e-05, "last_err": 0.0, "prev_value": 1.3410278688533814e-05, "change_rev": [22, 38]}, {"name": "benchmarks.PreprocessingBenchmarks.time_normalize_mag", "idx": 6, "pretty_name": "benchmarks.PreprocessingBenchmarks.time_normalize_mag(700, 'balanced', False)", "last_rev": 38, "last_value": 2.509206293705488e-05, "last_err": 0.0, "prev_value": 2.4699166284384423e-05, "change_rev": [22, 38]}, {"name": "benchmarks.PreprocessingBenchmarks.time_normalize_mag", "idx": 7, "pretty_name": "benchmarks.PreprocessingBenchmarks.time_normalize_mag(700, 'balanced', True)", "last_rev": 38, "last_value": 2.4661981132068916e-05, "last_err": 0.0, "prev_value": 2.4596026376125106e-05, "change_rev": [22, 38]}, {"name": "benchmarks.PreprocessingBenchmarks.time_normalize_mag", "idx": 8, "pretty_name": "benchmarks.PreprocessingBenchmarks.time_normalize_mag(700, 'g_only', False)", "last_rev": 38, "last_value": 2.4774656177166737e-05, "last_err": 9.447795381699337e-08, "prev_value": null, "change_rev": null}, {"name": "benchmarks.PreprocessingBenchmarks.time_normalize_mag", "idx": 9, "pretty_name": "benchmarks.PreprocessingBenchmarks.time_normalize_mag(700, 'g_only', True)", "last_rev": 38, "last_value": 2.4502409722219433e-05, "last_err": 0.0, "prev_value": 2.4673101545285377e-05, "change_rev": [22, 38]}, {"name": "benchmarks.PreprocessingBenchmarks.time_normalize_mag", "idx": 10, "pretty_name": "benchmarks.PreprocessingBenchmarks.time_normalize_mag(700, 'ri_only', False)", "last_rev": 38, "last_value": 2.4513499999991135e-05, "last_err": 0.0, "prev_value": 2.4535460093902486e-05, "change_rev": [22, 38]}, {"name": "benchmarks.PreprocessingBenchmarks.time_normalize_mag", "idx": 11, "pretty_name": "benchmarks.PreprocessingBenchmarks.time_normalize_mag(700, 'ri_only', True)", "last_rev": 38, "last_value": 2.4620941780814983e-05, "last_err": 0.0, "prev_value": 2.4693771126775887e-05, "change_rev": [22, 38]}, {"name": "benchmarks.PreprocessingBenchmarks.time_normalize_mag", "idx": 12, "pretty_name": "benchmarks.PreprocessingBenchmarks.time_normalize_mag(4096, 'balanced', False)", "last_rev": 38, "last_value": 7.742107194239367e-05, "last_err": 4.1613747159210314e-07, "prev_value": null, "change_rev": null}, {"name": "benchmarks.PreprocessingBenchmarks.time_normalize_mag", "idx": 13, "pretty_name": "benchmarks.PreprocessingBenchmarks.time_normalize_mag(4096, 'balanced', True)", "last_rev": 38, "last_value": 7.757689160840981e-05, "last_err": 0.0, "prev_value": 7.681458029205331e-05, "change_rev": [22, 38]}, {"name": "benchmarks.PreprocessingBenchmarks.time_normalize_mag", "idx": 14, "pretty_name": "benchmarks.PreprocessingBenchmarks.time_normalize_mag(4096, 'g_only', False)", "last_rev": 38, "last_value": 7.735836690644826e-05, "last_err": 2.970737561951709e-07, "prev_value": null, "change_rev": null}, {"name": "benchmarks.PreprocessingBenchmarks.time_normalize_mag", "idx": 15, "pretty_name": "benchmarks.PreprocessingBenchmarks.time_normalize_mag(4096, 'g_only', True)", "last_rev": 38, "last_value": 7.623740559441157e-05, "last_err": 0.0, "prev_value": 7.660005357139303e-05, "change_rev": [22, 38]}, {"name": "benchmarks.PreprocessingBenchmarks.time_normalize_mag", "idx": 16, "pretty_name": "benchmarks.PreprocessingBenchmarks.time_normalize_mag(4096, 'ri_only', False)", "last_rev": 38, "last_value": 7.72396834532823e-05, "last_err": 4.4251846269265643e-07, "prev_value": null, "change_rev": null}, {"name": "benchmarks.PreprocessingBenchmarks.time_normalize_mag", "idx": 17, "pretty_name": "benchmarks.PreprocessingBenchmarks.time_normalize_mag(4096, 'ri_only', True)", "last_rev": 38, "last_value": 7.642889928057735e-05, "last_err": 0.0, "prev_value": 7.841922340428933e-05, "change_rev": [22, 38]}, {"name": "benchmarks.PreprocessingBenchmarks.time_preprocess_lc", "idx": 0, "pretty_name": "benchmarks.PreprocessingBenchmarks.time_preprocess_lc(32, 'balanced', False)", "last_rev": 38, "last_value": 8.488053937001256e-05, "last_err": 0.0, "prev_value": 0.00012818780487803188, "change_rev": [22, 38]}, {"name": "benchmarks.PreprocessingBenchmarks.time_preprocess_lc", "idx": 1, "pretty_name": "benchmarks.PreprocessingBenchmarks.time_preprocess_lc(32, 'balanced', True)", "last_rev": 38, "last_value": 7.817322180447671e-05, "last_err": 0.0, "prev_value": 0.00012116649438202434, "change_rev": [22, 38]}, {"name": "benchmarks.PreprocessingBenchmarks.time_preprocess_lc", "idx": 2, "pretty_name": "benchmarks.PreprocessingBenchmarks.time_preprocess_lc(32, 'g_only', False)", "last_rev": 38, "last_value": 8.371882142853789e-05, "last_err": 0.0, "prev_value": 0.00012623341666658422, "change_rev": [22, 38]}, {"name": "benchmarks.PreprocessingBenchmarks.time_preprocess_lc", "idx": 3, "pretty_name": "benchmarks.PreprocessingBenchmarks.time_preprocess_lc(32, 'g_only', True)", "last_rev": 38, "last_value": 7.693561231884398e-05, "last_err": 0.0, "prev_value": 0.00011986164606749239, "change_rev": [22, 38]}, {"name": "benchmarks.PreprocessingBenchmarks.time_preprocess_lc", "idx": 4, "pretty_name": "benchmarks.PreprocessingBenchmarks.time_preprocess_lc(32, 'ri_only', False)", "last_rev": 38, "last_value": 8.511103600000069e-05, "last_err": 0.0, "prev_value": 0.00012727191071425028, "change_rev": [22, 38]}, {"name": "benchmarks.PreprocessingBenchmarks.time_preprocess_lc", "idx": 5, "pretty_name": "benchmarks.PreprocessingBenchmarks.time_preprocess_lc(32, 'ri_only', True)", "last_rev": 38, "last_value": 8.034841240876869e-05, "last_err": 0.0, "prev_value": 0.00012095405681825352, "change_rev": [22, 38]}, {"name": "benchmarks.PreprocessingBenchmarks.time_preprocess_lc", "idx": 6, "pretty_name": "benchmarks.PreprocessingBenchmarks.time_preprocess_lc(700, 'balanced', False)", "last_rev": 38, "last_value": 0.00013398140853655536, "last_err": 0.0, "prev_value": 0.00016183805882357912, "change_rev": [22, 38]}, {"name": "benchmarks.PreprocessingBenchmarks.time_preprocess_lc", "idx": 7, "pretty_name": "benchmarks.PreprocessingBenchmarks.time_preprocess_lc(700, 'balanced', True)", "last_rev": 38, "last_value": 0.00010604653921568425, "last_err": 0.0, "prev_value": 0.0001284446937500405, "change_rev": [22, 38]}, {"name": "benchmarks.PreprocessingBenchmarks.time_preprocess_lc", "idx": 8, "pretty_name": "benchmarks.PreprocessingBenchmarks.time_preprocess_lc(700, 'g_only', False)", "last_rev": 38, "last_value": 0.00012125578651685902, "last_err": 0.0, "prev_value": 0.00014202024324311432, "change_rev": [22, 38]}, {"name": "benchmarks.PreprocessingBenchmarks.time_preprocess_lc", "idx": 9, "pretty_name": "benchmarks.PreprocessingBenchmarks.time_preprocess_lc(700, 'g_only', True)", "last_rev": 38, "last_value": 9.142260869564745e-05, "last_err": 0.0, "prev_value": 0.00011701443820220192, "change_rev": [22, 38]}, {"name": "benchmarks.PreprocessingBenchmarks.time_preprocess_lc", "idx": 10, "pretty_name": "benchmarks.PreprocessingBenchmarks.time_preprocess_lc(700, 'ri_only', False)", "last_rev": 38, "last_value": 0.0001231813636363054, "last_err": 0.0, "prev_value": 0.00012949138607573732, "change_rev": [22, 38]}, {"name": "benchmarks.PreprocessingBenchmarks.time_preprocess_lc", "idx": 11, "pretty_name": "benchmarks.PreprocessingBenchmarks.time_preprocess_lc(700, 'ri_only', True)", "last_rev": 38, "last_value": 9.77634166666782e-05, "last_err": 0.0, "prev_value": 0.00010476736500010021, "change_rev": [22, 38]}, {"name": "benchmarks.PreprocessingBenchmarks.time_preprocess_lc", "idx": 12, "pretty_name": "benchmarks.PreprocessingBenchmarks.time_preprocess_lc(4096, 'balanced', False)", "last_rev": 38, "last_value": 0.00039019949999996584, "last_err": 0.0, "prev_value": 0.00037225008620675557, "change_rev": [22, 38]}, {"name": "benchmarks.PreprocessingBenchmarks.time_preprocess_lc", "idx": 13, "pretty_name": "benchmarks.PreprocessingBenchmarks.time_preprocess_lc(4096, 'balanced', True)", "last_rev": 38, "last_value": 0.00027614138461555917, "last_err": 0.0, "prev_value": 0.000252789439024417, "change_rev": [22, 38]}, {"name": "benchmarks.PreprocessingBenchmarks.time_preprocess_lc", "idx": 14, "pretty_name": "benchmarks.PreprocessingBenchmarks.time_preprocess_lc(4096, 'g_only', False)", "last_rev": 38, "last_value": 0.0002981030441175141, "last_err": 7.866342807751369e-06, "prev_value": null, "change_rev": null}, {"name": "benchmarks.PreprocessingBenchmarks.time_preprocess_lc", "idx": 15, "pretty_name": "benchmarks.PreprocessingBenchmarks.time_preprocess_lc(4096, 'g_only', True)", "last_rev": 38, "last_value": 0.0001705870312499469, "last_err": 0.0, "prev_value": 0.00019402409090916577, "change_rev": [22, 38]}, {"name": "benchmarks.PreprocessingBenchmarks.time_preprocess_lc", "idx": 16, "pretty_name": "benchmarks.PreprocessingBenchmarks.time_preprocess_lc(4096, 'ri_only', False)", "last_rev": 38, "last_value": 0.0003671291034483596, "last_err": 0.0, "prev_value": 0.0003740435892860867, "change_rev": [22, 38]}, {"name": "benchmarks.PreprocessingBenchmarks.time_preprocess_lc", "idx": 17, "pretty_name": "benchmarks.PreprocessingBenchmarks.time_preprocess_lc(4096, 'ri_only', True)", "last_rev": 38, "last_value": 0.00024935402380954486, "last_err": 0.0, "prev_value": 0.00025728877499986424, "change_rev": [22, 38]}]