[{"name": "benchmarks.PreprocessingBenchmarks.time_apply_strategy_beginning", "idx": 0, "pretty_name": "benchmarks.PreprocessingBenchmarks.time_apply_strategy_beginning(32, 'balanced', False)", "last_rev": 41, "last_value": 0.00010090893867885705, "last_err": 0.0, "prev_value": 9.453846460180094e-05, "change_rev": [37, 41]}, {"name": "benchmarks.PreprocessingBenchmarks.time_apply_strategy_beginning", "idx": 1, "pretty_name": "benchmarks.PreprocessingBenchmarks.time_apply_strategy_beginning(32, 'balanced', True)", "last_rev": 41, "last_value": 9.613061574077198e-05, "last_err": 0.0, "prev_value": 9.420014035087656e-05, "change_rev": [37, 41]}, {"name": "benchmarks.PreprocessingBenchmarks.time_apply_strategy_beginning", "idx": 2, "pretty_name": "benchmarks.PreprocessingBenchmarks.time_apply_strategy_beginning(32, 'g_only', False)", "last_rev": 41, "last_value": 9.539022522528637e-05, "last_err": 0.0, "prev_value": 9.190011304347008e-05, "change_rev": [37, 41]}, {"name": "benchmarks.PreprocessingBenchmarks.time_apply_strategy_beginning", "idx": 3, "pretty_name": "benchmarks.PreprocessingBenchmarks.time_apply_strategy_beginning(32, 'g_only', True)", "last_rev": 41, "last_value": 9.43715318183794e-05, "last_err": 0.0, "prev_value": 9.306249565220217e-05, "change_rev": [37, 41]}, {"name": "benchmarks.PreprocessingBenchmarks.time_apply_strategy_beginning", "idx": 4, "pretty_name": "benchmarks.PreprocessingBenchmarks.time_apply_strategy_beginning(32, 'ri_only', False)", "last_rev": 41, "last_value": 0.00010070168636389099, "last_err": 0.0, "prev_value": 9.611132589285428e-05, "change_rev": [37, 41]}, {"name": "benchmarks.PreprocessingBenchmarks.time_apply_strategy_beginning", "idx": 5, "pretty_name": "benchmarks.PreprocessingBenchmarks.time_apply_strategy_beginning(32, 'ri_only', True)", "last_rev": 41, "last_value": 9.660592592579346e-05, "last_err": 0.0, "prev_value": 9.418586403507452e-05, "change_rev": [37, 41]}, {"name": "benchmarks.PreprocessingBenchmarks.time_apply_strategy_beginning", "idx": 6, "pretty_name": "benchmarks.PreprocessingBenchmarks.time_apply_strategy_beginning(700, 'balanced', False)", "last_rev": 41, "last_value": 0.0001234069825584832, "last_err": 0.0, "prev_value": 0.00012007391666664091, "change_rev": [37, 41]}, {"name": "benchmarks.PreprocessingBenchmarks.time_apply_strategy_beginning", "idx": 7, "pretty_name": "benchmarks.PreprocessingBenchmarks.time_apply_strategy_beginning(700, 'balanced', True)", "last_rev": 41, "last_value": 0.00013206970930196424, "last_err": 0.0, "prev_value": 0.00011978169999997432, "change_rev": [37, 41]}, {"name": "benchmarks.PreprocessingBenchmarks.time_apply_strategy_beginning", "idx": 8, "pretty_name": "benchmarks.PreprocessingBenchmarks.time_apply_strategy_beginning(700, 'g_only', False)", "last_rev": 41, "last_value": 0.00011179926595736241, "last_err": 0.0, "prev_value": 0.0001076371313131679, "change_rev": [37, 41]}, {"name": "benchmarks.PreprocessingBenchmarks.time_apply_strategy_beginning", "idx": 9, "pretty_name": "benchmarks.PreprocessingBenchmarks.time_apply_strategy_beginning(700, 'g_only', True)", "last_rev": 41, "last_value": 0.00011149504787238855, "last_err": 0.0, "prev_value": 0.00010784836499997397, "change_rev": [37, 41]}, {"name": "benchmarks.PreprocessingBenchmarks.time_apply_strategy_beginning", "idx": 10, "pretty_name": "benchmarks.PreprocessingBenchmarks.time_apply_strategy_beginning(700, 'ri_only', False)", "last_rev": 41, "last_value": 0.0001199345329672434, "last_err": 0.0, "prev_value": 0.00011421708064513462, "change_rev": [37, 41]}, {"name": "benchmarks.PreprocessingBenchmarks.time_apply_strategy_beginning", "idx": 11, "pretty_name": "benchmarks.PreprocessingBenchmarks.time_apply_strategy_beginning(700, 'ri_only', True)", "last_rev": 41, "last_value": 0.0001167970833332927, "last_err": 0.0, "prev_value": 0.00011425034946237932, "change_rev": [37, 41]}, {"name": "benchmarks.PreprocessingBenchmarks.time_apply_strategy_beginning", "idx": 12, "pretty_name": "benchmarks.PreprocessingBenchmarks.time_apply_strategy_beginning(4096, 'balanced', False)", "last_rev": 41, "last_value": 0.0003031173333327944, "last_err": 0.0, "prev_value": 0.00029486504285724125, "change_rev": [37, 41]}, {"name": "benchmarks.PreprocessingBenchmarks.time_apply_strategy_beginning", "idx": 13, "pretty_name": "benchmarks.PreprocessingBenchmarks.time_apply_strategy_beginning(4096, 'balanced', True)", "last_rev": 41, "last_value": 0.00030635436111165544, "last_err": 0.0, "prev_value": 0.00029503632432437144, "change_rev": [37, 41]}, {"name": "benchmarks.PreprocessingBenchmarks.time_apply_strategy_beginning", "idx": 14, "pretty_name": "benchmarks.PreprocessingBenchmarks.time_apply_strategy_beginning(4096, 'g_only', False)", "last_rev": 41, "last_value": 0.00019517888392885294, "last_err": 0.0, "prev_value": 0.0001868009000000241, "change_rev": [37, 41]}, {"name": "benchmarks.PreprocessingBenchmarks.time_apply_strategy_beginning", "idx": 15, "pretty_name": "benchmarks.PreprocessingBenchmarks.time_apply_strategy_beginning(4096, 'g_only', True)", "last_rev": 41, "last_value": 0.00019011614285651443, "last_err": 0.0, "prev_value": 0.00018653619090911052, "change_rev": [37, 41]}, {"name": "benchmarks.PreprocessingBenchmarks.time_apply_strategy_beginning", "idx": 16, "pretty_name": "benchmarks.PreprocessingBenchmarks.time_apply_strategy_beginning(4096, 'ri_only', False)", "last_rev": 41, "last_value": 0.0002760344487193414, "last_err": 0.0, "prev_value": 0.00026206403658534673, "change_rev": [37, 41]}, {"name": "benchmarks.PreprocessingBenchmarks.time_apply_strategy_beginning", "idx": 17, "pretty_name": "benchmarks.PreprocessingBenchmarks.time_apply_strategy_beginning(4096, 'ri_only', True)", "last_rev": 41, "last_value": 0.0002845884861102377, "last_err": 0.0, "prev_value": 0.00026586075000007976, "change_rev": [37, 41]}, {"name": "benchmarks.PreprocessingBenchmarks.time_argsort", "idx": 0, "pretty_name": "benchmarks.PreprocessingBenchmarks.time_argsort(32, 'balanced', False)", "last_rev": 41, "last_value": 3.631830172984787e-06, "last_err": 2.9533588935437934e-08, "prev_value": null, "change_rev": null}, {"name": "benchmarks.PreprocessingBenchmarks.time_argsort", "idx": 1, "pretty_name": "benchmarks.PreprocessingBenchmarks.time_argsort(32, 'balanced', True)", "last_rev": 41, "last_value": 1.0173485454588031e-07, "last_err": 1.7517553013073374e-09, "prev_value": null, "change_rev": null}, {"name": "benchmarks.PreprocessingBenchmarks.time_argsort", "idx": 2, "pretty_name": "benchmarks.PreprocessingBenchmarks.time_argsort(32, 'g_only', False)", "last_rev": 41, "last_value": 3.572832613741422e-06, "last_err": 1.6162118136273487e-08, "prev_value": null, "change_rev": null}, {"name": "benchmarks.PreprocessingBenchmarks.time_argsort", "idx": 3, "pretty_name": "benchmarks.PreprocessingBenchmarks.time_argsort(32, 'g_only', True)", "last_rev": 41, "last_value": 1.0163458181825615e-07, "last_err": 1.1787272609422095e-09, "prev_value": null, "change_rev": null}, {"name": "benchmarks.PreprocessingBenchmarks.time_argsort", "idx": 4, "pretty_name": "benchmarks.PreprocessingBenchmarks.time_argsort(32, 'ri_only', False)", "last_rev": 41, "last_value": 3.5767968385937726e-06, "last_err": 0.0, "prev_value": 3.5587365884991934e-06, "change_rev": [37, 41]}, {"name": "benchmarks.PreprocessingBenchmarks.time_argsort", "idx": 5, "pretty_name": "benchmarks.PreprocessingBenchmarks.time_argsort(32, 'ri_only', True)", "last_rev": 41, "last_value": 1.0131748517481176e-07, "last_err": 0.0, "prev_value": 1.0603877348609126e-07, "change_rev": [37, 41]}, {"name": "benchmarks.PreprocessingBenchmarks.time_argsort", "idx": 6, "pretty_name": "benchmarks.PreprocessingBenchmarks.time_argsort(700, 'balanced', False)", "last_rev": 41, "last_value": 1.8150722222196728e-05, "last_err": 0.0, "prev_value": 1.816276061121316e-05, "change_rev": [37, 41]}, {"name": "benchmarks.PreprocessingBenchmarks.time_argsort", "idx": 7, "pretty_name": "benchmarks.PreprocessingBenchmarks.time_argsort(700, 'balanced', True)", "last_rev": 41, "last_value": 9.922994191081889e-08, "last_err": 0.0, "prev_value": 1.0416389545456054e-07, "change_rev": [37, 41]}, {"name": "benchmarks.PreprocessingBenchmarks.time_argsort", "idx": 8, "pretty_name": "benchmarks.PreprocessingBenchmarks.time_argsort(700, 'g_only', False)", "last_rev": 41, "last_value": 1.8132033840955695e-05, "last_err": 0.0, "prev_value": 1.7989196517408937e-05, "change_rev": [37, 41]}, {"name": "benchmarks.PreprocessingBenchmarks.time_argsort", "idx": 9, "pretty_name": "benchmarks.PreprocessingBenchmarks.time_argsort(700, 'g_only', True)", "last_rev": 41, "last_value": 1.001803181818094e-07, "last_err": 1.6187532941002299e-09, "prev_value": null, "change_rev": null}, {"name": "benchmarks.PreprocessingBenchmarks.time_argsort", "idx": 10, "pretty_name": "benchmarks.PreprocessingBenchmarks.time_argsort(700, 'ri_only', False)", "last_rev": 41, "last_value": 1.8247631756765286e-05, "last_err": 8.563999462005376e-08, "prev_value": null, "change_rev": null}, {"name": "benchmarks.PreprocessingBenchmarks.time_argsort", "idx": 11, "pretty_name": "benchmarks.PreprocessingBenchmarks.time_argsort(700, 'ri_only', True)", "last_rev": 41, "last_value": 1.0162164999989252e-07, "last_err": 2.0761053754380806e-09, "prev_value": null, "change_rev": null}, {"name": "benchmarks.PreprocessingBenchmarks.time_argsort", "idx": 12, "pretty_name": "benchmarks.PreprocessingBenchmarks.time_argsort(4096, 'balanced', False)", "last_rev": 41, "last_value": 8.889865163891434e-05, "last_err": 0.0, "prev_value": 8.882644672134293e-05, "change_rev": [37, 41]}, {"name": "benchmarks.PreprocessingBenchmarks.time_argsort", "idx": 13, "pretty_name": "benchmarks.PreprocessingBenchmarks.time_argsort(4096, 'balanced', True)", "last_rev": 41, "last_value": 9.880576968531734e-08, "last_err": 0.0, "prev_value": 1.0291855454547452e-07, "change_rev": [37, 41]}, {"name": "benchmarks.PreprocessingBenchmarks.time_argsort", "idx": 14, "pretty_name": "benchmarks.PreprocessingBenchmarks.time_argsort(4096, 'g_only', False)", "last_rev": 41, "last_value": 8.855244214820901e-05, "last_err": 0.0, "prev_value": 8.85075650406598e-05, "change_rev": [37, 41]}, {"name": "benchmarks.PreprocessingBenchmarks.time_argsort", "idx": 15, "pretty_name": "benchmarks.PreprocessingBenchmarks.time_argsort(4096, 'g_only', True)", "last_rev": 41, "last_value": 9.9429244499407e-08, "last_err": 0.0, "prev_value": 1.0142735000002935e-07, "change_rev": [37, 41]}, {"name": "benchmarks.PreprocessingBenchmarks.time_argsort", "idx": 16, "pretty_name": "benchmarks.PreprocessingBenchmarks.time_argsort(4096, 'ri_only', False)", "last_rev": 41, "last_value": 8.904768852462496e-05, "last_err": 3.601504404754858e-07, "prev_value": null, "change_rev": null}, {"name": "benchmarks.PreprocessingBenchmarks.time_argsort", "idx": 17, "pretty_name": "benchmarks.PreprocessingBenchmarks.time_argsort(4096, 'ri_only', True)", "last_rev": 41, "last_value": 9.901489244601798e-08, "last_err": 0.0, "prev_value": 1.037347954545192e-07, "change_rev": [37, 41]}, {"name": "benchmarks.PreprocessingBenchmarks.time_normalize_mag", "idx": 0, "pretty_name": "benchmarks.PreprocessingBenchmarks.time_normalize_mag(32, 'balanced', False)", "last_rev": 41, "last_value": 1.5861329758772066e-05, "last_err": 0.0, "prev_value": 1.3428854192745881e-05, "change_rev": [37, 41]}, {"name": "benchmarks.PreprocessingBenchmarks.time_normalize_mag", "idx": 1, "pretty_name": "benchmarks.PreprocessingBenchmarks.time_normalize_mag(32, 'balanced', True)", "last_rev": 41, "last_value": 1.400740177351939e-05, "last_err": 1.0777517791004228e-07, "prev_value": null, "change_rev": null}, {"name": "benchmarks.PreprocessingBenchmarks.time_normalize_mag", "idx": 2, "pretty_name": "benchmarks.PreprocessingBenchmarks.time_normalize_mag(32, 'g_only', False)", "last_rev": 41, "last_value": 1.3892699067911524e-05, "last_err": 0.0, "prev_value": 1.33960456790121e-05, "change_rev": [37, 41]}, {"name": "benchmarks.PreprocessingBenchmarks.time_normalize_mag", "idx": 3, "pretty_name": "benchmarks.PreprocessingBenchmarks.time_normalize_mag(32, 'g_only', True)", "last_rev": 41, "last_value": 1.3953621352711635e-05, "last_err": 0.0, "prev_value": 1.3401238881836374e-05, "change_rev": [37, 41]}, {"name": "benchmarks.PreprocessingBenchmarks.time_normalize_mag", "idx": 4, "pretty_name": "benchmarks.PreprocessingBenchmarks.time_normalize_mag(32, 'ri_only', False)", "last_rev": 41, "last_value": 1.3656269132629093e-05, "last_err": 1.1164685350764719e-07, "prev_value": null, "change_rev": null}, {"name": "benchmarks.PreprocessingBenchmarks.time_normalize_mag", "idx": 5, "pretty_name": "benchmarks.PreprocessingBenchmarks.time_normalize_mag(32, 'ri_only', True)", "last_rev": 41, "last_value": 1.3933811333420939e-05, "last_err": 0.0, "prev_value": 1.3468129870126227e-05, "change_rev": [37, 41]}, {"name": "benchmarks.PreprocessingBenchmarks.time_normalize_mag", "idx": 6, "pretty_name": "benchmarks.PreprocessingBenchmarks.time_normalize_mag(700, 'balanced', False)", "last_rev": 41, "last_value": 2.5113800947842265e-05, "last_err": 2.475036304325323e-07, "prev_value": null, "change_rev": null}, {"name": "benchmarks.PreprocessingBenchmarks.time_normalize_mag", "idx": 7, "pretty_name": "benchmarks.PreprocessingBenchmarks.time_normalize_mag(700, 'balanced', True)", "last_rev": 41, "last_value": 2.5056355477820443e-05, "last_err": 0.0, "prev_value": 2.4661981132068916e-05, "change_rev": [37, 41]}, {"name": "benchmarks.PreprocessingBenchmarks.time_normalize_mag", "idx": 8, "pretty_name": "benchmarks.PreprocessingBenchmarks.time_normalize_mag(700, 'g_only', False)", "last_rev": 41, "last_value": 2.5038167441866023e-05, "last_err": 9.118592183111802e-08, "prev_value": null, "change_rev": null}, {"name": "benchmarks.PreprocessingBenchmarks.time_normalize_mag", "idx": 9, "pretty_name": "benchmarks.PreprocessingBenchmarks.time_normalize_mag(700, 'g_only', True)", "last_rev": 41, "last_value": 2.5070232311329704e-05, "last_err": 2.6088180738142146e-07, "prev_value": null, "change_rev": null}, {"name": "benchmarks.PreprocessingBenchmarks.time_normalize_mag", "idx": 10, "pretty_name": "benchmarks.PreprocessingBenchmarks.time_normalize_mag(700, 'ri_only', False)", "last_rev": 41, "last_value": 2.53263087557405e-05, "last_err": 0.0, "prev_value": 2.4513499999991135e-05, "change_rev": [37, 41]}, {"name": "benchmarks.PreprocessingBenchmarks.time_normalize_mag", "idx": 11, "pretty_name": "benchmarks.PreprocessingBenchmarks.time_normalize_mag(700, 'ri_only', True)", "last_rev": 41, "last_value": 2.5342189411704192e-05, "last_err": 0.0, "prev_value": 2.4620941780814983e-05, "change_rev": [37, 41]}, {"name": "benchmarks.PreprocessingBenchmarks.time_normalize_mag", "idx": 12, "pretty_name": "benchmarks.PreprocessingBenchmarks.time_normalize_mag(4096, 'balanced', False)", "last_rev": 41, "last_value": 7.742107194239367e-05, "last_err": 2.7860682366302255e-07, "prev_value": null, "change_rev": null}, {"name": "benchmarks.PreprocessingBenchmarks.time_normalize_mag", "idx": 13, "pretty_name": "benchmarks.PreprocessingBenchmarks.time_normalize_mag(4096, 'balanced', True)", "last_rev": 41, "last_value": 7.741783453210498e-05, "last_err": 0.0, "prev_value": 7.757689160840981e-05, "change_rev": [37, 41]}, {"name": "benchmarks.PreprocessingBenchmarks.time_normalize_mag", "idx": 14, "pretty_name": "benchmarks.PreprocessingBenchmarks.time_normalize_mag(4096, 'g_only', False)", "last_rev": 41, "last_value": 7.708613405863775e-05, "last_err": 0.0, "prev_value": 7.725588076921825e-05, "change_rev": [37, 41]}, {"name": "benchmarks.PreprocessingBenchmarks.time_normalize_mag", "idx": 15, "pretty_name": "benchmarks.PreprocessingBenchmarks.time_normalize_mag(4096, 'g_only', True)", "last_rev": 41, "last_value": 7.660005357139303e-05, "last_err": 4.356127883999598e-07, "prev_value": null, "change_rev": null}, {"name": "benchmarks.PreprocessingBenchmarks.time_normalize_mag", "idx": 16, "pretty_name": "benchmarks.PreprocessingBenchmarks.time_normalize_mag(4096, 'ri_only', False)", "last_rev": 41, "last_value": 7.692438848918507e-05, "last_err": 3.54540142843454e-07, "prev_value": null, "change_rev": null}, {"name": "benchmarks.PreprocessingBenchmarks.time_normalize_mag", "idx": 17, "pretty_name": "benchmarks.PreprocessingBenchmarks.time_normalize_mag(4096, 'ri_only', True)", "last_rev": 41, "last_value": 7.698137142873358e-05, "last_err": 2.271131201073201e-07, "prev_value": 7.854050367657053e-05, "change_rev": [22, 37]}, {"name": "benchmarks.PreprocessingBenchmarks.time_preprocess_lc", "idx": 0, "pretty_name": "benchmarks.PreprocessingBenchmarks.time_preprocess_lc(32, 'balanced', False)", "last_rev": 41, "last_value": 8.941917241390362e-05, "last_err": 0.0, "prev_value": 8.488053937001256e-05, "change_rev": [37, 41]}, {"name": "benchmarks.PreprocessingBenchmarks.time_preprocess_lc", "idx": 1, "pretty_name": "benchmarks.PreprocessingBenchmarks.time_preprocess_lc(32, 'balanced', True)", "last_rev": 41, "last_value": 8.197160887066861e-05, "last_err": 0.0, "prev_value": 7.817322180447671e-05, "change_rev": [37, 41]}, {"name": "benchmarks.PreprocessingBenchmarks.time_preprocess_lc", "idx": 2, "pretty_name": "benchmarks.PreprocessingBenchmarks.time_preprocess_lc(32, 'g_only', False)", "last_rev": 41, "last_value": 8.371882142853789e-05, "last_err": 1.668705920936725e-06, "prev_value": 0.00012623341666658422, "change_rev": [22, 37]}, {"name": "benchmarks.PreprocessingBenchmarks.time_preprocess_lc", "idx": 3, "pretty_name": "benchmarks.PreprocessingBenchmarks.time_preprocess_lc(32, 'g_only', True)", "last_rev": 41, "last_value": 8.010703461597866e-05, "last_err": 2.0544561165685103e-05, "prev_value": null, "change_rev": null}, {"name": "benchmarks.PreprocessingBenchmarks.time_preprocess_lc", "idx": 4, "pretty_name": "benchmarks.PreprocessingBenchmarks.time_preprocess_lc(32, 'ri_only', False)", "last_rev": 41, "last_value": 8.85443613445877e-05, "last_err": 0.0, "prev_value": 8.511103600000069e-05, "change_rev": [37, 41]}, {"name": "benchmarks.PreprocessingBenchmarks.time_preprocess_lc", "idx": 5, "pretty_name": "benchmarks.PreprocessingBenchmarks.time_preprocess_lc(32, 'ri_only', True)", "last_rev": 41, "last_value": 8.163391923097572e-05, "last_err": 0.0, "prev_value": 8.034841240876869e-05, "change_rev": [37, 41]}, {"name": "benchmarks.PreprocessingBenchmarks.time_preprocess_lc", "idx": 6, "pretty_name": "benchmarks.PreprocessingBenchmarks.time_preprocess_lc(700, 'balanced', False)", "last_rev": 41, "last_value": 0.00013445965822783467, "last_err": 0.0, "prev_value": 0.00013398140853655536, "change_rev": [37, 41]}, {"name": "benchmarks.PreprocessingBenchmarks.time_preprocess_lc", "idx": 7, "pretty_name": "benchmarks.PreprocessingBenchmarks.time_preprocess_lc(700, 'balanced', True)", "last_rev": 41, "last_value": 0.00010780762886614744, "last_err": 0.0, "prev_value": 0.00010604653921568425, "change_rev": [37, 41]}, {"name": "benchmarks.PreprocessingBenchmarks.time_preprocess_lc", "idx": 8, "pretty_name": "benchmarks.PreprocessingBenchmarks.time_preprocess_lc(700, 'g_only', False)", "last_rev": 41, "last_value": 0.00012361752976156973, "last_err": 8.10824926964231e-07, "prev_value": 0.0001432291891891328, "change_rev": [22, 37]}, {"name": "benchmarks.PreprocessingBenchmarks.time_preprocess_lc", "idx": 9, "pretty_name": "benchmarks.PreprocessingBenchmarks.time_preprocess_lc(700, 'g_only', True)", "last_rev": 41, "last_value": 9.673551785738255e-05, "last_err": 0.0, "prev_value": 9.142260869564745e-05, "change_rev": [37, 41]}, {"name": "benchmarks.PreprocessingBenchmarks.time_preprocess_lc", "idx": 10, "pretty_name": "benchmarks.PreprocessingBenchmarks.time_preprocess_lc(700, 'ri_only', False)", "last_rev": 41, "last_value": 0.00012648640853562827, "last_err": 2.1919248766846357e-06, "prev_value": null, "change_rev": null}, {"name": "benchmarks.PreprocessingBenchmarks.time_preprocess_lc", "idx": 11, "pretty_name": "benchmarks.PreprocessingBenchmarks.time_preprocess_lc(700, 'ri_only', True)", "last_rev": 41, "last_value": 0.00010200807766966922, "last_err": 0.0, "prev_value": 9.77634166666782e-05, "change_rev": [37, 41]}, {"name": "benchmarks.PreprocessingBenchmarks.time_preprocess_lc", "idx": 12, "pretty_name": "benchmarks.PreprocessingBenchmarks.time_preprocess_lc(4096, 'balanced', False)", "last_rev": 41, "last_value": 0.0004001520925953628, "last_err": 0.0, "prev_value": 0.00039019949999996584, "change_rev": [37, 41]}, {"name": "benchmarks.PreprocessingBenchmarks.time_preprocess_lc", "idx": 13, "pretty_name": "benchmarks.PreprocessingBenchmarks.time_preprocess_lc(4096, 'balanced', True)", "last_rev": 41, "last_value": 0.00027614138461555917, "last_err": 1.3748548692566576e-05, "prev_value": null, "change_rev": null}, {"name": "benchmarks.PreprocessingBenchmarks.time_preprocess_lc", "idx": 14, "pretty_name": "benchmarks.PreprocessingBenchmarks.time_preprocess_lc(4096, 'g_only', False)", "last_rev": 41, "last_value": 0.0002981030441175141, "last_err": 8.547736896789685e-06, "prev_value": null, "change_rev": null}, {"name": "benchmarks.PreprocessingBenchmarks.time_preprocess_lc", "idx": 15, "pretty_name": "benchmarks.PreprocessingBenchmarks.time_preprocess_lc(4096, 'g_only', True)", "last_rev": 41, "last_value": 0.00019402409090916577, "last_err": 1.132040068040187e-05, "prev_value": null, "change_rev": null}, {"name": "benchmarks.PreprocessingBenchmarks.time_preprocess_lc", "idx": 16, "pretty_name": "benchmarks.PreprocessingBenchmarks.time_preprocess_lc(4096, 'ri_only', False)", "last_rev": 41, "last_value": 0.0003727456250024781, "last_err": 3.01232415573367e-06, "prev_value": null, "change_rev": null}, {"name": "benchmarks.PreprocessingBenchmarks.time_preprocess_lc", "idx": 17, "pretty_name": "benchmarks.PreprocessingBenchmarks.time_preprocess_lc(4096, 'ri_only', True)", "last_rev": 41, "last_value": 0.0002621008624998922, "last_err": 4.244631104551453e-06, "prev_value": null, "change_rev": null}]